{"_path":"/book/system-config","_dir":"book","_draft":false,"_partial":false,"_locale":"","title":"System config","description":"","director":"MY","time":"2025","img":"17/1.png","plan":"100,100","body":{"type":"root","children":[{"type":"element","tag":"book-content","props":{":by":"director",":img":"img",":plan":"plan",":title":"title"},"children":[{"type":"element","tag":"text-title","props":{"t":"Nix"},"children":[]},{"type":"element","tag":"h1","props":{"id":"nix-2"},"children":[{"type":"text","value":"Nix 2"}]},{"type":"element","tag":"p","props":{},"children":[{"type":"text","value":"也是视奸群u萌看到的，了解了下发现是 2003 年就开始发布了，至今已经 22 年了。（第一印象还以为是一个发行版，确实有，"},{"type":"element","tag":"a","props":{"href":"https://nixos.org/","rel":["nofollow"]},"children":[{"type":"text","value":"NixOS"}]},{"type":"text","value":"）。a"}]},{"type":"text","value":"\n\n\n\n\n\n\n\n\n\n\n\n\n\n\n"},{"type":"element","tag":"table","props":{},"children":[{"type":"element","tag":"thead","props":{},"children":[{"type":"element","tag":"tr","props":{},"children":[{"type":"element","tag":"th","props":{},"children":[{"type":"text","value":"command"}]},{"type":"element","tag":"th","props":{},"children":[{"type":"text","value":"info"}]},{"type":"element","tag":"th","props":{},"children":[{"type":"text","value":"e.g"}]}]}]},{"type":"element","tag":"tbody","props":{},"children":[{"type":"element","tag":"tr","props":{},"children":[{"type":"element","tag":"td","props":{},"children":[{"type":"text","value":"nix-shell"}]},{"type":"element","tag":"td","props":{},"children":[{"type":"text","value":"创建一个隔离环境"}]},{"type":"element","tag":"td","props":{},"children":[{"type":"text","value":"nix-shell -p nodejs --run 'node -v'"}]}]}]}]}]}],"toc":{"title":"","searchDepth":2,"depth":2,"links":[]}},"_type":"markdown","_id":"content:book:system-config.md","_source":"content","_file":"book/system-config.md","_extension":"md"}