{"id":"00303fa5-a887-475f-a15f-fd6dbb2bb87d","timestamp":1745591919709,"matcher":{"static":{},"wildcard":{},"dynamic":{}},"prerendered":["/test","/tools/kcal","/","/book","/des","/link","/sec","/about","/book/key-note","/book/game-life","/book/criminal_minds","/book/unicode-explained","/book/24-hour","/book/journey-to-the-west","/book/tools-config","/book/seven-languages-in-seven-weeks-bruce-a-tate","/book/attacking-network-protocols","/book/fate-of-moon-jae-in","/sec/tcmedical","/sec/turing","/sec/yadugroup","/sec/edrawmax","/sec/iptv","/sec/ycrenfu","/sec/github-misconfiguration"]}