{"id":"4b60e9e7-953d-4079-9023-648a49ee03dd","timestamp":1747489993521,"matcher":{"static":{},"wildcard":{},"dynamic":{}},"prerendered":["/tools/kcal","/tools/plan","/","/book","/des","/sec","/link","/about","/book/24-hour","/book/journey-to-the-west","/book/criminal_minds","/book/key-note","/book/game-life","/book/attacking-network-protocols","/book/fate-of-moon-jae-in","/book/seven-languages-in-seven-weeks-bruce-a-tate","/book/unicode-explained","/sec/tcmedical","/sec/yadugroup","/sec/turing","/sec/ycrenfu","/sec/github-misconfiguration","/sec/iptv","/sec/edrawmax"]}