{"id":"df3bdc79-6a72-4325-b500-5a836dc26063","timestamp":1750607649776,"matcher":{"static":{},"wildcard":{},"dynamic":{}},"prerendered":["/tools/kcal","/tools/plan","/","/des","/link","/sec","/book","/sec/tcmedical","/sec/yadugroup","/sec/turing","/about","/book/spine-2d","/book/24-hour","/book/game-life","/book/criminal_minds","/book/journey-to-the-west","/book/fate-of-moon-jae-in","/sec/ycrenfu","/sec/github-misconfiguration","/sec/iptv","/sec/edrawmax","/book/cve-learn","/book/unicode-explained","/book/attacking-network-protocols","/book/key-note","/outher/ethereum-website-pr","/book/seven-languages-in-seven-weeks-bruce-a-tate"]}